yaml_srcinfo_loader/__init__.py
yaml_srcinfo_loader/loader.py
yaml_srcinfo_loader/srcinfo.py
pyyaml_srcinfo_loader-0.0.1.888772944.dist-info/LICENSE
pyyaml_srcinfo_loader-0.0.1.888772944.dist-info/METADATA
pyyaml_srcinfo_loader-0.0.1.888772944.dist-info/WHEEL
pyyaml_srcinfo_loader-0.0.1.888772944.dist-info/RECORD
